AUTHORS
CHANGELOG
LICENSE
README.md
android_clean_app.py
setup.cfg
setup.py
android_resource_remover.egg-info/PKG-INFO
android_resource_remover.egg-info/SOURCES.txt
android_resource_remover.egg-info/dependency_links.txt
android_resource_remover.egg-info/entry_points.txt
android_resource_remover.egg-info/namespace_packages.txt
android_resource_remover.egg-info/requires.txt
android_resource_remover.egg-info/top_level.txt
test/test_clean_app.py