Metadata-Version: 1.1
Name: android-resource-remover
Version: 0.1.7
Summary: Android resource remover
Home-page: https://github.com/KeepSafe/android-resource-remover/
Author: Keepsafe
Author-email: support@getkeepsafe.com
License: Apache
Keywords: android
Platform: UNKNOWN
Classifier: License :: OSI Approved :: BSD License
Classifier: Intended Audience :: Developers
Classifier: Programming Language :: Python
